reloadrable/__init__.py
reloadrable/reloadable.py
reloadrable/reloadable_handler.py
reloadrable/reloadable_manager.py
Reloadrable-1.0.0.dist-info/LICENSE
Reloadrable-1.0.0.dist-info/METADATA
Reloadrable-1.0.0.dist-info/WHEEL
Reloadrable-1.0.0.dist-info/top_level.txt
Reloadrable-1.0.0.dist-info/RECORD
