Metadata-Version: 2.1
Name: Reloadrable
Version: 1.0.0
Summary: Reloadr's hot-reloading Python code + a bunch of little extensions.
Home-page: https://github.com/urushiyama/reloadrable
Author: Yuta Urushiyama
Author-email: aswif10flis1ntkb@gmail.com
License: LGPLv3
Platform: UNKNOWN
Classifier: Programming Language :: Python :: 3
Classifier: License :: OSI Approved :: GNU General Public License v3 (GPLv3)
Requires-Python: >=3.7
Requires-Dist: watchdog
